speclogician/__init__.py
speclogician/agent/__init__.py
speclogician/agent/funcs.py
speclogician/cmd/__init__.py
speclogician/cmd/agent_cmd.py
speclogician/cmd/data_cmd.py
speclogician/cmd/model_cmd.py
speclogician/cmd/overlay_cmd.py
speclogician/cmd/scenario_cmd.py
speclogician/cmd/state_cmd.py
speclogician/data/__init__.py
speclogician/data/artifact.py
speclogician/data/container.py
speclogician/data/mapping.py
speclogician/data/refs.py
speclogician/data/reports.py
speclogician/data/traces.py
speclogician/llms/__init__.py
speclogician/llms/llmtools.py
speclogician/llms/overlay.py
speclogician/main.py
speclogician/modeling/__init__.py
speclogician/modeling/component.py
speclogician/modeling/conflict.py
speclogician/modeling/domain.py
speclogician/modeling/model.py
speclogician/modeling/predicates.py
speclogician/modeling/report.py
speclogician/modeling/scenario.py
speclogician/py.typed
speclogician/sl_cmd.py
speclogician/state/__init__.py
speclogician/state/change.py
speclogician/state/state.py
speclogician/tui/box.tcss
speclogician/tui/tui.py
speclogician/utils/__init__.py
speclogician/utils/imx.py
speclogician/utils/load.py
speclogician/utils/prompt.md
speclogician-0.0.0.dev1.dist-info/WHEEL
speclogician-0.0.0.dev1.dist-info/METADATA
speclogician-0.0.0.dev1.dist-info/RECORD
